[
    {
        "domain": ".x.com",
        "expirationDate": 1756799317.31204,
        "hostOnly": false,
        "httpOnly": true,
        "name": "auth_token",
        "path": "/",
        "sameSite": "no_restriction",
        "secure": true,
        "session": false,
        "storeId": "unspecified",
        "value": "3f0fe8415e35661ec93a20dd8dae970fee5d86d5"
    },
    {
        "domain": ".x.com",
        "expirationDate": 1722248251.705269,
        "hostOnly": false,
        "httpOnly": false,
        "name": "gt",
        "path": "/",
        "sameSite": "unspecified",
        "secure": true,
        "session": false,
        "storeId": "unspecified",
        "value": "1817829291054490079"
    },
    {
        "domain": ".x.com",
        "expirationDate": 1753775251.171973,
        "hostOnly": false,
        "httpOnly": false,
        "name": "guest_id",
        "path": "/",
        "sameSite": "no_restriction",
        "secure": true,
        "session": false,
        "storeId": "unspecified",
        "value": "v1%3A172223924782483184"
    },
    {
        "domain": ".x.com",
        "expirationDate": 1753775348.050644,
        "hostOnly": false,
        "httpOnly": false,
        "name": "twid",
        "path": "/",
        "sameSite": "no_restriction",
        "secure": true,
        "session": false,
        "storeId": "unspecified",
        "value": "u%3D711658031285727232"
    },
    {
        "domain": "x.com",
        "hostOnly": true,
        "httpOnly": false,
        "name": "lang",
        "path": "/",
        "sameSite": "unspecified",
        "secure": false,
        "session": true,
        "storeId": "unspecified",
        "value": "en"
    },
    {
        "domain": ".x.com",
        "expirationDate": 1753775319.021868,
        "hostOnly": false,
        "httpOnly": false,
        "name": "night_mode",
        "path": "/",
        "sameSite": "no_restriction",
        "secure": true,
        "session": false,
        "storeId": "unspecified",
        "value": "2"
    },
    {
        "domain": ".x.com",
        "expirationDate": 1722325718.044894,
        "hostOnly": false,
        "httpOnly": true,
        "name": "att",
        "path": "/",
        "sameSite": "no_restriction",
        "secure": true,
        "session": false,
        "storeId": "unspecified",
        "value": "1-rRTMvSlZjvQDDB0VMWgt4eeeT6X8ttwMvyc9rf5k"
    },
    {
        "domain": ".x.com",
        "expirationDate": 1756799317.650286,
        "hostOnly": false,
        "httpOnly": false,
        "name": "ct0",
        "path": "/",
        "sameSite": "lax",
        "secure": true,
        "session": false,
        "storeId": "unspecified",
        "value": "c0aadd83e4dee4371dc10453288c8e9a04bbba850dbf3ae76e142f74eedea26e23fa85ad0d5f15c2b6e01d149189aa1b40124f5d3f37ef148ce30f0d44712f7cdb91e4626c0c33fce85eb79bba9573d6"
    },
    {
        "domain": ".x.com",
        "expirationDate": 1756799320.850091,
        "hostOnly": false,
        "httpOnly": false,
        "name": "guest_id_ads",
        "path": "/",
        "sameSite": "no_restriction",
        "secure": true,
        "session": false,
        "storeId": "unspecified",
        "value": "v1%3A172223924782483184"
    },
    {
        "domain": ".x.com",
        "expirationDate": 1756799320.850213,
        "hostOnly": false,
        "httpOnly": false,
        "name": "guest_id_marketing",
        "path": "/",
        "sameSite": "no_restriction",
        "secure": true,
        "session": false,
        "storeId": "unspecified",
        "value": "v1%3A172223924782483184"
    },
    {
        "domain": ".x.com",
        "expirationDate": 1756799317.311822,
        "hostOnly": false,
        "httpOnly": true,
        "name": "kdt",
        "path": "/",
        "sameSite": "unspecified",
        "secure": true,
        "session": false,
        "storeId": "unspecified",
        "value": "CGw7XbMNOOrHLzAybIxo42AVuoM6gRJ4QYOJf0en"
    },
    {
        "domain": ".x.com",
        "expirationDate": 1756799320.850315,
        "hostOnly": false,
        "httpOnly": false,
        "name": "personalization_id",
        "path": "/",
        "sameSite": "no_restriction",
        "secure": true,
        "session": false,
        "storeId": "unspecified",
        "value": "\"v1_gTCIHJQ1yEQVmxYtdK/aXA==\""
    }
]